ls_tui-0.1.0.dist-info/licenses/LICENSE
lx/__init__.py
lx/__main__.py
lx/app.py
lx/file_node.py
lx/file_utils.py
lx/styles.tcss
lx/tree_widget.py
ls_tui-0.1.0.dist-info/METADATA
ls_tui-0.1.0.dist-info/WHEEL
ls_tui-0.1.0.dist-info/entry_points.txt
ls_tui-0.1.0.dist-info/top_level.txt
ls_tui-0.1.0.dist-info/RECORD
