Metadata-Version: 2.4
Name: ls-tui
Version: 0.1.0
Summary: Interactive Directory Tree Explorer - A modern TUI for navigating directories
Author-email: Your Name <your.email@example.com>
License-Expression: MIT
Project-URL: Homepage, https://github.com/yourusername/lx
Project-URL: Documentation, https://github.com/yourusername/lx#readme
Project-URL: Repository, https://github.com/yourusername/lx
Project-URL: Issues, https://github.com/yourusername/lx/issues
Project-URL: Changelog, https://github.com/yourusername/lx/blob/main/CHANGELOG.md
Keywords: directory,tree,explorer,tui,terminal,file-browser,navigator
Classifier: Development Status :: 4 - Beta
Classifier: Environment :: Console
Classifier: Intended Audience :: Developers
Classifier: Intended Audience :: System Administrators
Classifier: Operating System :: OS Independent
Classifier: Operating System :: POSIX :: Linux
Classifier: Operating System :: MacOS
Classifier: Programming Language :: Python :: 3
Classifier: Programming Language :: Python :: 3.10
Classifier: Programming Language :: Python :: 3.11
Classifier: Programming Language :: Python :: 3.12
Classifier: Programming Language :: Python :: 3.13
Classifier: Programming Language :: Python :: 3.14
Classifier: Topic :: System :: Filesystems
Classifier: Topic :: System :: Shells
Classifier: Topic :: Utilities
Classifier: Typing :: Typed
Requires-Python: >=3.10
License-File: LICENSE
Requires-Dist: textual>=0.40.0
Requires-Dist: pathspec>=0.11.0
Provides-Extra: dev
Requires-Dist: pytest>=7.0.0; extra == "dev"
Requires-Dist: pytest-cov>=4.0.0; extra == "dev"
Requires-Dist: black>=23.0.0; extra == "dev"
Requires-Dist: pylint>=2.17.0; extra == "dev"
Requires-Dist: flake8>=6.0.0; extra == "dev"
Requires-Dist: mypy>=1.0.0; extra == "dev"
Dynamic: license-file
